parquest/__init__.py
parquest/main.py
parquest/raw/__init__.py
parquest/raw/commands.py
parquest/raw/extract/__init__.py
parquest/raw/extract/commands.py
parquest/structured/__init__.py
parquest/structured/commands.py
parquest/structured/convert/__init__.py
parquest/structured/convert/commands.py
parquest/structured/specs/__init__.py
parquest/structured/specs/commands.py
parquest-0.0.15.dist-info/LICENSE
parquest-0.0.15.dist-info/METADATA
parquest-0.0.15.dist-info/WHEEL
parquest-0.0.15.dist-info/entry_points.txt
parquest-0.0.15.dist-info/top_level.txt
parquest-0.0.15.dist-info/RECORD
