Metadata-Version: 2.1
Name: parquest
Version: 0.0.15
Summary: A command line application that helps converting raw data into highly-structured data in Parquet.
Author-email: Zaid Waqi <zaidwaqi@gmail.com>
License: GPLv3
Project-URL: Homepage, https://github.com/zaidwaqi/parquest
Project-URL: Issues, https://github.com/zaidwaqi/parquest/issues
Classifier: Programming Language :: Python :: 3
Classifier: License :: OSI Approved :: GNU General Public License v3 (GPLv3)
Classifier: Operating System :: OS Independent
Requires-Python: >=3.11
License-File: LICENSE
